stop_discord_phishing/__init__.py
stop_discord_phishing/amount.py
stop_discord_phishing/check.py
stop_discord_phishing/list.py
stop_discord_phishing-1.0.0.dist-info/METADATA
stop_discord_phishing-1.0.0.dist-info/WHEEL
stop_discord_phishing-1.0.0.dist-info/RECORD
