Metadata-Version: 2.1
Name: stop-discord-phishing
Version: 1.0.0
Summary: 
Author: sdmway
Author-email: github@sdmway.tech
Requires-Python: >=3.8,<4.0
Classifier: Programming Language :: Python :: 3
Classifier: Programming Language :: Python :: 3.8
Classifier: Programming Language :: Python :: 3.9
Classifier: Programming Language :: Python :: 3.10
Classifier: Programming Language :: Python :: 3.11
Classifier: Programming Language :: Python :: 3.12
Requires-Dist: aiohttp[speedups] (>=3.8.0,<4.0.0)
Requires-Dist: cachetools (>=5.3.3,<6.0.0)
